{
  "users": [
    {
      "username": "user1",
      "password": "12345"
    }
  ],
  "products": [
    {
      "id": 1,
      "name": "computer 12",
      "price": "560009",
      "checked": true
    },
    {
      "id": 2,
      "name": "phone 13",
      "price": 3000,
      "checked": true
    },
    {
      "id": 3,
      "name": "printer",
      "price": 600,
      "checked": false
    },
    {
      "name": "toto",
      "price": "567",
      "checked": true,
      "id": 4
    },
    {
      "name": "hjkj",
      "price": "hjk",
      "checked": false,
      "id": 5
    },
    {
      "name": "a",
      "price": "100",
      "checked": true,
      "id": 7
    },
    {
      "name": "tt",
      "price": "567",
      "checked": false,
      "id": 9
    },
    {
      "name": "mouad",
      "price": "78788",
      "checked": false,
      "id": 10
    },
    {
      "name": "h",
      "price": "88",
      "checked": false,
      "id": 11
    }
  ]
}